CHANGELOG.md
LICENSE
tfimm/__init__.py
tfimm/architectures/__init__.py
tfimm/architectures/cait.py
tfimm/architectures/convmixer.py
tfimm/architectures/convnext.py
tfimm/architectures/efficientnet.py
tfimm/architectures/efficientnet_blocks.py
tfimm/architectures/efficientnet_builder.py
tfimm/architectures/lora/README.md
tfimm/architectures/lora/__init__.py
tfimm/architectures/lora/convnext.py
tfimm/architectures/lora/factory.py
tfimm/architectures/lora/layers.py
tfimm/architectures/lora/registry.py
tfimm/architectures/mlp_mixer.py
tfimm/architectures/pit.py
tfimm/architectures/poolformer.py
tfimm/architectures/pvt.py
tfimm/architectures/pvt_v2.py
tfimm/architectures/resnet.py
tfimm/architectures/resnetv2.py
tfimm/architectures/segment_anything/__init__.py
tfimm/architectures/segment_anything/common.py
tfimm/architectures/segment_anything/image_encoder.py
tfimm/architectures/segment_anything/mask_decoder.py
tfimm/architectures/segment_anything/predictor.py
tfimm/architectures/segment_anything/prompt_encoder.py
tfimm/architectures/segment_anything/sam.py
tfimm/architectures/segment_anything/torch/__init__.py
tfimm/architectures/segment_anything/torch/automatic_mask_generator.py
tfimm/architectures/segment_anything/torch/build_sam.py
tfimm/architectures/segment_anything/torch/modeling/__init__.py
tfimm/architectures/segment_anything/torch/modeling/common.py
tfimm/architectures/segment_anything/torch/modeling/image_encoder.py
tfimm/architectures/segment_anything/torch/modeling/mask_decoder.py
tfimm/architectures/segment_anything/torch/modeling/prompt_encoder.py
tfimm/architectures/segment_anything/torch/modeling/sam.py
tfimm/architectures/segment_anything/torch/modeling/transformer.py
tfimm/architectures/segment_anything/torch/predictor.py
tfimm/architectures/segment_anything/torch/utils/__init__.py
tfimm/architectures/segment_anything/torch/utils/amg.py
tfimm/architectures/segment_anything/torch/utils/onnx.py
tfimm-0.2.14.dist-info/LICENSE
tfimm-0.2.14.dist-info/METADATA
tfimm-0.2.14.dist-info/WHEEL
tfimm-0.2.14.dist-info/RECORD
