Metadata-Version: 2.1
Name: tfimm
Version: 0.2.14
Summary: TensorFlow port of PyTorch Image Models (timm) - image models with pretrained weights
Home-page: https://github.com/martinsbruveris/tensorflow-image-models
License: Apache-2.0
Keywords: tensorfow,pretrained models,visual transformer
Author: Martins Bruveris
Author-email: martins.bruveris@gmail.com
Requires-Python: >=3.8,<3.11
Classifier: Development Status :: 3 - Alpha
Classifier: Intended Audience :: Education
Classifier: Intended Audience :: Science/Research
Classifier: License :: OSI Approved :: Apache Software License
Classifier: Operating System :: OS Independent
Classifier: Programming Language :: Python :: 3
Classifier: Programming Language :: Python :: 3.8
Classifier: Programming Language :: Python :: 3.9
Classifier: Programming Language :: Python :: 3.10
Classifier: Programming Language :: Python :: 3
Classifier: Programming Language :: Python :: 3.7
Classifier: Programming Language :: Python :: 3.8
Classifier: Topic :: Scientific/Engineering
Classifier: Topic :: Scientific/Engineering :: Artificial Intelligence
Classifier: Topic :: Software Development
Classifier: Topic :: Software Development :: Libraries
Classifier: Topic :: Software Development :: Libraries :: Python Modules
Provides-Extra: docs
Requires-Dist: markdown (>=3.3.6,<4.0.0)
Requires-Dist: numpy
Requires-Dist: sphinx ; extra == "docs"
Requires-Dist: sphinx-rtd-theme ; extra == "docs"
Requires-Dist: tensorflow (>=2.8,<3.0)
Project-URL: Repository, https://github.com/martinsbruveris/tensorflow-image-models
